{
	"textures": {
		"particle": "blocks/planks_big_oak",
		"0": "blocks/planks_big_oak"
	},
	"elements": [
		{
			"name": "Latte Süd",
			"from": [6.75, 0, 6.5],
			"to": [9.25, 14.775, 9.5],
			"faces": {
				"north": {"uv": [0, 12.5, 16, 14.75], "texture": "#0", "rotation": 90},
				"east": {"uv": [0, 12.5, 16, 14.75], "texture": "#0", "rotation": 90},
				"south": {"uv": [0, 12.5, 16, 14.75], "texture": "#0", "rotation": 90},
				"west": {"uv": [0, 12.5, 16, 14.75], "texture": "#0"},
				"up": {"uv": [0, 12.5, 16, 14.75], "texture": "#0", "rotation": 90},
				"down": {"uv": [0, 12.5, 16, 14.75], "texture": "#0", "rotation": 90}
			}
		},
		{
			"name": "Pfahl Süd",
			"from": [6, 0, 7],
			"to": [10, 16, 9],
			"faces": {
				"north": {"uv": [0, 12.25, 16, 15.75], "texture": "#0", "rotation": 90, "cullface": "north"},
				"east": {"uv": [0, 12.25, 16, 15.75], "texture": "#0", "rotation": 90, "cullface": "north"},
				"south": {"uv": [0, 12.25, 16, 15.75], "texture": "#0", "rotation": 90, "cullface": "north"},
				"west": {"uv": [0, 12.25, 16, 15.75], "texture": "#0", "rotation": 90, "cullface": "north"},
				"up": {"uv": [8, 8.75, 12, 10.75], "texture": "#0", "cullface": "up"},
				"down": {"uv": [9.5, 12.5, 13.5, 14.5], "texture": "#0", "cullface": "down"}
			}
		}
	]
}